Workbook

Sheet Respostas
A1: Nome | B1: Idade | C1: Ocupação | D1: Frequência de compra online (P2) | E1: Ticket médio R$ (P3) | F1: Já comprou outlet/brechó? (P4) | G1: Já recebeu peça com defeito? (P6) | H1: O que fez nesse caso (P6) | I1: Como julga se o desconto é justo (P7) | J1: O que precisaria saber para comprar (P8) | K1: Cenário A — desconto mín. | L1: Cenário B — desconto mín. | M1: Cenário C — desconto mín. | N1: Cenário D — desconto mín. | O1: Cenário que mais incomodou (P9) | P1: Uso vs. aparência (P10) | Q1: Reação à ideia (P11) | R1: Confia na nota? (P12) | S1: O que impediria de usar (P13)
A2: Sharon Biggs | B2: 23 | C2: arquiteta | D2: ~1x por mês | E2: 350 | F2: S | G2: S | H2: consertou | I2: feeling | J2: saber qual é o defeito e o quanto impacta o uso e longevidade do produto | K2: 15 | L2: 35 | M2: 40 | N2: NC | O2: D | P2: Uso | Q2: acha que tudo funcionaria, ideia muito sustentável | R2: Sim | S2: nada
A3: Maria do Carmo Luiz | B3: 65 | C3: empregada doméstica | D3: Poucas vezes por ano | E3: 55 | F3: S | G3: S | H3: consertou | I3: sempre acha justo | J3: se dá para consertar | K3: 50 | L3: NC | M3: 10 | N3: 10 | O3: B | P3: Aparência | Q3: achou boa apenas para produtos cujo defeito atrapalha o uso da peça | R3: Em parte | S3: nada
A4: Vitória Ribeiro | B4: 21 | C4: estudante de administração | D4: ~1x por mês | E4: 350 | F4: S | G4: S | H4: guardou | I4: analisa o histórico da loja | J4: gostaria de poder ver em pessoa | K4: 40 | L4: NC | M4: 50 | N4: NC | O4: D | P4: Uso | Q4: acha boa apenas para peças de marcas conhecidas com defeitos pequenos | R4: Em parte | S4: avaliações ruins
A5: Karl Tocantins | B5: 23 | C5: estudente de economia | D5: Nunca | E5: 250 | F5: S | G5: N | H5: N/A | I5: analisa o histórico da loja | J5: N/A | K5: 40 | L5: NC | M5: NC | N5: NC | O5: B | P5: Aparência | Q5: acha ruim, nunca compraria roupas com defeito | R5: Em parte | S5: N/A
A6: Nicole Couto | B6: 21 | C6: estudante de arquitetura | D6: Poucas vezes por ano | E6: 350 | F6: S | G6: N | H6: N/A | I6: analise o tamanho do desconto | J6: se for um defeito imperceptível | K6: 10 | L6: 30 | M6: 35 | N6: NC | O6: D | P6: Uso | Q6: acha boa | R6: Sim | S6: avaliações ruins
A7: João Pedro Ribeiro | B7: 21 | C7: estudante de direito | D7: Poucas vezes por ano | E7: 350 | F7: S | G7: N | H7: N/A | I7: analisa o custo benefício | J7: se for um defeito pequeno | K7: 10 | L7: 30 | M7: 50 | N7: NC | O7: D | P7: Depende | Q7: acha boa, contanto que dê para ver fotos | R7: Sim | S7: avaliações ruins
A8: Francisco Carvalho | B8: 24 | C8: trainee | D8: Poucas vezes por ano | E8: 125 | F8: S | G8: S | H8: guardou | I8: compara o preço com outras marcas | J8: saber qual é o defeito e se for algo que o incomoda | K8: 0 | L8: 35 | M8: NC | N8: 50 | O8: C | P8: Uso | Q8: acha boa | R8: Sim | S8: descontos ruins
A9: Joaquim de Azambuja | B9: 17 | C9: estudante | D9: Poucas vezes por ano | E9: 250 | F9: S | G9: S | H9: guardou | I9: depende do produto | J9: se o defeito afeta a aparência | K9: 10 | L9: 25 | M9: 25 | N9: 40 | O9: D | P9: Aparência | Q9: acha boa, mas que podem haver problemas logísticos | R9: Sim | S9: venda de produtos roubados

Sheet Resumo
B2: Resumo das entrevistas
B5: 1. Amostra
B6: Entrevistas registradas | C6: =SUMPRODUCT(--((Respostas!B2:B9<>"")+(Respostas!D2:D9<>"")+(Respostas!K2:K9<>"")>0)) -> 8
B7: Idade média | C7: =IF($C$6=0,"—",IFERROR(AVERAGE(Respostas!B2:B9),"—")) -> 26.875
B8: Ticket médio declarado | C8: =IF($C$6=0,"—",IFERROR(AVERAGE(Respostas!E2:E9),"—")) -> 260
B9: Já comprou outlet / brechó / app de usado | C9: =IFERROR(COUNTIF(Respostas!F2:F9,"S")/$C$6,"—") -> 1
B10: Já recebeu peça com defeito | C10: =IFERROR(COUNTIF(Respostas!G2:G9,"S")/$C$6,"—") -> 0.625
B12: 2. Desconto mínimo aceito, por cenário (Bloco 4)
B13: Cenário | C13: Média | D13: Mediana | E13: Mínimo | F13: Máximo | G13: Nº "NC" | H13: Critérios testados
B14: A — mancha 2 cm no forro (invisível) | C14: =IF($C$6=0,"—",IFERROR(AVERAGE(Respostas!K2:K9),"—")) -> 21.875 | D14: =IF($C$6=0,"—",IFERROR(MEDIAN(Respostas!K2:K9),"—")) -> 12.5 | E14: =IF($C$6=0,"—",IFERROR(MIN(Respostas!K2:K9),"—")) -> 0 | F14: =IF($C$6=0,"—",IFERROR(MAX(Respostas!K2:K9),"—")) -> 50 | G14: =COUNTIF(Respostas!K2:K9,"NC") -> 0 | H14: estético + escondido + pequeno
B15: B — costura torta 10 cm, visível | C15: =IF($C$6=0,"—",IFERROR(AVERAGE(Respostas!L2:L9),"—")) -> 31 | D15: =IF($C$6=0,"—",IFERROR(MEDIAN(Respostas!L2:L9),"—")) -> 30 | E15: =IF($C$6=0,"—",IFERROR(MIN(Respostas!L2:L9),"—")) -> 25 | F15: =IF($C$6=0,"—",IFERROR(MAX(Respostas!L2:L9),"—")) -> 35 | G15: =COUNTIF(Respostas!L2:L9,"NC") -> 3 | H15: estético + visível + médio
B16: C — botão faltando | C16: =IF($C$6=0,"—",IFERROR(AVERAGE(Respostas!M2:M9),"—")) -> 35 | D16: =IF($C$6=0,"—",IFERROR(MEDIAN(Respostas!M2:M9),"—")) -> 37.5 | E16: =IF($C$6=0,"—",IFERROR(MIN(Respostas!M2:M9),"—")) -> 10 | F16: =IF($C$6=0,"—",IFERROR(MAX(Respostas!M2:M9),"—")) -> 50 | G16: =COUNTIF(Respostas!M2:M9,"NC") -> 2 | H16: funcional + visível + leve
B17: D — zíper quebrado | C17: =IF($C$6=0,"—",IFERROR(AVERAGE(Respostas!N2:N9),"—")) -> 33.333333 | D17: =IF($C$6=0,"—",IFERROR(MEDIAN(Respostas!N2:N9),"—")) -> 40 | E17: =IF($C$6=0,"—",IFERROR(MIN(Respostas!N2:N9),"—")) -> 10 | F17: =IF($C$6=0,"—",IFERROR(MAX(Respostas!N2:N9),"—")) -> 50 | G17: =COUNTIF(Respostas!N2:N9,"NC") -> 5 | H17: funcional + visível + grave
B20: 3. Calibração dos pesos do simulador
B23: Desconto-base (defeito estético, escondido, pequeno) | C23: =IFERROR(C14,"—") -> 21.875 | D23: média do cenário A
B24: Efeito de o defeito ficar visível | C24: =IFERROR(C15-C14,"—") -> 9.125 | D24: média B menos média A
B25: Efeito de o defeito afetar o uso | C25: =IFERROR(C17-C15,"—") -> 2.3333333 | D25: média D menos média B
B26: Defeito funcional leve vs. estético visível | C26: =IFERROR(C16-C15,"—") -> 4 | D26: média C menos média B
B27: Teto observado de desconto | C27: =IF($C$6=0,"—",IFERROR(MAX(C14:C17),"—")) -> 35 | D27: maior média entre os quatro cenários
B28: Total de recusas ("NC") em todos os cenários | C28: =SUM(G14:G17) -> 10 | D28: quanto maior, mais gente que nenhum desconto converte
B30: 4. Percepção qualitativa (contagens)
B31: Pergunta | C31: Opção | D31: Nº de respostas | E31: % da amostra
B32: P11 — cenário que mais incomodou | C32: A | D32: =COUNTIF(Respostas!O2:O9,"A") -> 0 | E32: =IFERROR(D32/$C$6,"—") -> 0
C33: B | D33: =COUNTIF(Respostas!O2:O9,"B") -> 2 | E33: =IFERROR(D33/$C$6,"—") -> 0.25
C34: C | D34: =COUNTIF(Respostas!O2:O9,"C") -> 1 | E34: =IFERROR(D34/$C$6,"—") -> 0.125
C35: D | D35: =COUNTIF(Respostas!O2:O9,"D") -> 5 | E35: =IFERROR(D35/$C$6,"—") -> 0.625
B37: P12 — o que pesa mais na decisão | C37: Uso | D37: =COUNTIF(Respostas!P2:P9,"Uso") -> 4 | E37: =IFERROR(D37/$C$6,"—") -> 0.5
C38: Aparência | D38: =COUNTIF(Respostas!P2:P9,"Aparência") -> 3 | E38: =IFERROR(D38/$C$6,"—") -> 0.375
C39: Depende | D39: =COUNTIF(Respostas!P2:P9,"Depende") -> 1 | E39: =IFERROR(D39/$C$6,"—") -> 0.125
B41: P14 — confia na nota de severidade | C41: Sim | D41: =COUNTIF(Respostas!R2:R9,"Sim") -> 5 | E41: =IFERROR(D41/$C$6,"—") -> 0.625
C42: Em parte | D42: =COUNTIF(Respostas!R2:R9,"Em parte") -> 3 | E42: =IFERROR(D42/$C$6,"—") -> 0.375
C43: Não | D43: =COUNTIF(Respostas!R2:R9,"Não") -> 0 | E43: =IFERROR(D43/$C$6,"—") -> 0
